nvgpu/__init__.py
nvgpu/__main__.py
nvgpu/agent.py
nvgpu/list_gpus.py
nvgpu/master.py
nvgpu/nvml.py
nvgpu/webapp.py
nvgpu-0.9.0.dist-info/LICENSE
nvgpu-0.9.0.dist-info/METADATA
nvgpu-0.9.0.dist-info/WHEEL
nvgpu-0.9.0.dist-info/entry_points.txt
nvgpu-0.9.0.dist-info/top_level.txt
nvgpu-0.9.0.dist-info/RECORD
