Metadata-Version: 1.1
Name: nvgpu
Version: 0.9.0
Summary: NVIDIA GPU tools
Home-page: https://github.com/rossumai/nvgpu
Author: Bohumir Zamecnik, Rossum
Author-email: bohumir.zamecnik@rossum.ai
License: MIT
Platform: UNKNOWN
Classifier: Development Status :: 3 - Alpha
Classifier: Intended Audience :: Developers
Classifier: Intended Audience :: Science/Research
Classifier: License :: OSI Approved :: MIT License
Classifier: Programming Language :: Python :: 2
Classifier: Programming Language :: Python :: 3
Classifier: Operating System :: POSIX :: Linux
